Metadata-Version: 2.1
Name: ttf2dxf
Version: 0.1.0
Summary: simple python based ttf to dxf converter
Home-page: https://github.com/multigcs/ttf2dxf/
Author: Oliver Dippel
Author-email: o.dippel@gmx.de
License: LICENSE
Platform: UNKNOWN
License-File: LICENSE
